LICENSE
README.md
pyproject.toml
setup.cfg
setup.py
creload/__init__.py
creload/lazyimport.py
creload/subprocess_call.py
creload.egg-info/PKG-INFO
creload.egg-info/SOURCES.txt
creload.egg-info/dependency_links.txt
creload.egg-info/not-zip-safe
creload.egg-info/top_level.txt