Metadata-Version: 2.1
Name: creload
Version: 1.0.0
Summary: Import inside a forked process to allow temporary imports of C extensions
Home-page: UNKNOWN
Author: Tobias Bergkvist
License: MIT
Platform: unix
Platform: linux
Platform: osx
Classifier: Programming Language :: Python :: 3
Requires-Python: >=3.7
